django_kelove_database/__init__.py
django_kelove_database/admin.py
django_kelove_database/apps.py
django_kelove_database/ckfinder/__init__.py
django_kelove_database/ckfinder/acl.py
django_kelove_database/ckfinder/adapter.py
django_kelove_database/ckfinder/ckfinder.py
django_kelove_database/ckfinder/commands.py
django_kelove_database/ckfinder/exception.py
django_kelove_database/ckfinder/response.py
django_kelove_database/ckfinder/util.py
django_kelove_database/db/__init__.py
django_kelove_database/db/backends/__init__.py
django_kelove_database/db/backends/base/__init__.py
django_kelove_database/db/backends/base/doc.py
django_kelove_database/db/backends/mysql/__init__.py
django_kelove_database/db/backends/mysql/base.py
django_kelove_database/db/backends/mysql/doc.py
django_kelove_database/db/backends/mysql/schema.py
django_kelove_database/db/fields.py
django_kelove_database/forms/__init__.py
django_kelove_database/forms/fields.py
django_kelove_database/forms/widgets.py
django_kelove_database/kelove_settings.py
django_kelove_database/migrations/0001_initial.py
django_kelove_database/migrations/0002_alter_ckfinderresource_id.py
django_kelove_database/migrations/0003_alter_ckfinderresource_options.py
django_kelove_database/migrations/__init__.py
django_kelove_database/models.py
django_kelove_database/static/kelove_database/bootstrap4/css/bootstrap.min.css
django_kelove_database/static/kelove_database/bootstrap4/js/bootstrap.bundle.min.js
django_kelove_database/static/kelove_database/ckeditor/build/ckeditor.js
django_kelove_database/static/kelove_database/ckeditor/build/ckeditor.js.map
django_kelove_database/static/kelove_database/ckeditor/build/translations/af.js
django_kelove_database/static/kelove_database/ckeditor/build/translations/ar.js
django_kelove_database/static/kelove_database/ckeditor/build/translations/ast.js
django_kelove_database/static/kelove_database/ckeditor/build/translations/az.js
django_kelove_database-2.0.0.dist-info/LICENSE
django_kelove_database-2.0.0.dist-info/WHEEL
django_kelove_database-2.0.0.dist-info/METADATA
django_kelove_database-2.0.0.dist-info/RECORD
