Metadata-Version: 2.1
Name: django-kelove-database
Version: 2.0.0
Summary: DJANGO 数据库增强插件
Home-page: https://gitee.com/itxq/django-kelove-database
License: Apache-2.0
Keywords: django,django-kelove,django-kelove-database
Author: IT小强xqitw.cn
Author-email: mail@xqitw.cn
Maintainer: IT小强xqitw.cn
Maintainer-email: mail@xqitw.cn
Requires-Python: >=3.8,<4.0
Classifier: Development Status :: 3 - Alpha
Classifier: Framework :: Django :: 3.1
Classifier: Intended Audience :: Developers
Classifier: License :: OSI Approved :: Apache Software License
Classifier: Natural Language :: Chinese (Simplified)
Classifier: Programming Language :: Python :: 3
Classifier: Programming Language :: Python :: 3.10
Classifier: Programming Language :: Python :: 3.6
Classifier: Programming Language :: Python :: 3.7
Classifier: Programming Language :: Python :: 3.8
Classifier: Programming Language :: Python :: 3.9
Requires-Dist: django-kelove-setting (>=2.0,<3.0)
Project-URL: Documentation, https://gitee.com/itxq/django-kelove-database/blob/master/README.md
Project-URL: Repository, https://gitee.com/itxq/django-kelove-database.git
